fastcli/__init__.py
fastcli/cli.py
fastcli/exceptions.py
fastcli/fast_helper.py
fastcli/helpers.py
fastcli/log.py
wallarm_fast_cli-1.0.0.dist-info/LICENSE
wallarm_fast_cli-1.0.0.dist-info/METADATA
wallarm_fast_cli-1.0.0.dist-info/WHEEL
wallarm_fast_cli-1.0.0.dist-info/entry_points.txt
wallarm_fast_cli-1.0.0.dist-info/top_level.txt
wallarm_fast_cli-1.0.0.dist-info/RECORD
