Metadata-Version: 2.1
Name: wallarm-fast-cli
Version: 1.0.0
Summary: A Wallarm FAST CLI tool for executing tests and getting results from the command line.
Home-page: https://github.com/faloker/wallarm-fast-cli
License: MIT
Platform: UNKNOWN
Classifier: Topic :: Security
Classifier: Topic :: Software Development :: Quality Assurance
Classifier: Topic :: Software Development :: Testing
Classifier: Topic :: Software Development :: Libraries :: Python Modules
Classifier: Programming Language :: Python :: 3.7
Classifier: Intended Audience :: Developers
Classifier: Intended Audience :: Information Technology
Requires-Dist: click (==7.0)
Requires-Dist: requests (==2.23.0)
